{"nodes": [{"id": "d_java_debt_settlement_app_frontend_src_screens_adddebtscreen_js", "label": "AddDebtScreen.js", "file_type": "code", "source_file": "D:\\java\\debt-settlement\\App-frontend\\src\\screens\\AddDebtScreen.js", "source_location": "L1"}, {"id": "screens_adddebtscreen_adddebtscreen", "label": "AddDebtScreen()", "file_type": "code", "source_file": "D:\\java\\debt-settlement\\App-frontend\\src\\screens\\AddDebtScreen.js", "source_location": "L8"}], "edges": [{"source": "d_java_debt_settlement_app_frontend_src_screens_adddebtscreen_js", "target": "react", "relation": "imports_from", "confidence": "EXTRACTED", "source_file": "D:\\java\\debt-settlement\\App-frontend\\src\\screens\\AddDebtScreen.js", "source_location": "L1", "weight": 1.0}, {"source": "d_java_debt_settlement_app_frontend_src_screens_adddebtscreen_js", "target": "react_native", "relation": "imports_from", "confidence": "EXTRACTED", "source_file": "D:\\java\\debt-settlement\\App-frontend\\src\\screens\\AddDebtScreen.js", "source_location": "L2", "weight": 1.0}, {"source": "d_java_debt_settlement_app_frontend_src_screens_adddebtscreen_js", "target": "react_native_safe_area_context", "relation": "imports_from", "confidence": "EXTRACTED", "source_file": "D:\\java\\debt-settlement\\App-frontend\\src\\screens\\AddDebtScreen.js", "source_location": "L3", "weight": 1.0}, {"source": "d_java_debt_settlement_app_frontend_src_screens_adddebtscreen_js", "target": "d_java_debt_settlement_app_frontend_src_store_usestore", "relation": "imports_from", "confidence": "EXTRACTED", "source_file": "D:\\java\\debt-settlement\\App-frontend\\src\\screens\\AddDebtScreen.js", "source_location": "L4", "weight": 1.0}, {"source": "d_java_debt_settlement_app_frontend_src_screens_adddebtscreen_js", "target": "d_java_debt_settlement_app_frontend_src_theme_theme", "relation": "imports_from", "confidence": "EXTRACTED", "source_file": "D:\\java\\debt-settlement\\App-frontend\\src\\screens\\AddDebtScreen.js", "source_location": "L5", "weight": 1.0}, {"source": "d_java_debt_settlement_app_frontend_src_screens_adddebtscreen_js", "target": "lucide_react_native", "relation": "imports_from", "confidence": "EXTRACTED", "source_file": "D:\\java\\debt-settlement\\App-frontend\\src\\screens\\AddDebtScreen.js", "source_location": "L6", "weight": 1.0}, {"source": "d_java_debt_settlement_app_frontend_src_screens_adddebtscreen_js", "target": "screens_adddebtscreen_adddebtscreen", "relation": "contains", "confidence": "EXTRACTED", "source_file": "D:\\java\\debt-settlement\\App-frontend\\src\\screens\\AddDebtScreen.js", "source_location": "L8", "weight": 1.0}], "raw_calls": [{"caller_nid": "screens_adddebtscreen_adddebtscreen", "callee": "useStore", "is_member_call": false, "source_file": "D:\\java\\debt-settlement\\App-frontend\\src\\screens\\AddDebtScreen.js", "source_location": "L9"}, {"caller_nid": "screens_adddebtscreen_adddebtscreen", "callee": "useState", "is_member_call": false, "source_file": "D:\\java\\debt-settlement\\App-frontend\\src\\screens\\AddDebtScreen.js", "source_location": "L11"}, {"caller_nid": "screens_adddebtscreen_adddebtscreen", "callee": "useState", "is_member_call": false, "source_file": "D:\\java\\debt-settlement\\App-frontend\\src\\screens\\AddDebtScreen.js", "source_location": "L12"}, {"caller_nid": "screens_adddebtscreen_adddebtscreen", "callee": "useState", "is_member_call": false, "source_file": "D:\\java\\debt-settlement\\App-frontend\\src\\screens\\AddDebtScreen.js", "source_location": "L13"}, {"caller_nid": "screens_adddebtscreen_adddebtscreen", "callee": "useState", "is_member_call": false, "source_file": "D:\\java\\debt-settlement\\App-frontend\\src\\screens\\AddDebtScreen.js", "source_location": "L14"}, {"caller_nid": "screens_adddebtscreen_adddebtscreen", "callee": "useState", "is_member_call": false, "source_file": "D:\\java\\debt-settlement\\App-frontend\\src\\screens\\AddDebtScreen.js", "source_location": "L15"}, {"caller_nid": "screens_adddebtscreen_adddebtscreen", "callee": "useState", "is_member_call": false, "source_file": "D:\\java\\debt-settlement\\App-frontend\\src\\screens\\AddDebtScreen.js", "source_location": "L16"}, {"caller_nid": "screens_adddebtscreen_adddebtscreen", "callee": "useState", "is_member_call": false, "source_file": "D:\\java\\debt-settlement\\App-frontend\\src\\screens\\AddDebtScreen.js", "source_location": "L17"}]}