{"nodes": [{"id": "d_java_debt_settlement_app_frontend_src_screens_landingscreen_js", "label": "LandingScreen.js", "file_type": "code", "source_file": "D:\\java\\debt-settlement\\App-frontend\\src\\screens\\LandingScreen.js", "source_location": "L1"}, {"id": "screens_landingscreen_landingscreen", "label": "LandingScreen()", "file_type": "code", "source_file": "D:\\java\\debt-settlement\\App-frontend\\src\\screens\\LandingScreen.js", "source_location": "L17"}], "edges": [{"source": "d_java_debt_settlement_app_frontend_src_screens_landingscreen_js", "target": "react", "relation": "imports_from", "confidence": "EXTRACTED", "source_file": "D:\\java\\debt-settlement\\App-frontend\\src\\screens\\LandingScreen.js", "source_location": "L1", "weight": 1.0}, {"source": "d_java_debt_settlement_app_frontend_src_screens_landingscreen_js", "target": "react_native", "relation": "imports_from", "confidence": "EXTRACTED", "source_file": "D:\\java\\debt-settlement\\App-frontend\\src\\screens\\LandingScreen.js", "source_location": "L2", "weight": 1.0}, {"source": "d_java_debt_settlement_app_frontend_src_screens_landingscreen_js", "target": "react_native_safe_area_context", "relation": "imports_from", "confidence": "EXTRACTED", "source_file": "D:\\java\\debt-settlement\\App-frontend\\src\\screens\\LandingScreen.js", "source_location": "L3", "weight": 1.0}, {"source": "d_java_debt_settlement_app_frontend_src_screens_landingscreen_js", "target": "d_java_debt_settlement_app_frontend_src_theme_theme", "relation": "imports_from", "confidence": "EXTRACTED", "source_file": "D:\\java\\debt-settlement\\App-frontend\\src\\screens\\LandingScreen.js", "source_location": "L4", "weight": 1.0}, {"source": "d_java_debt_settlement_app_frontend_src_screens_landingscreen_js", "target": "native", "relation": "imports_from", "confidence": "EXTRACTED", "source_file": "D:\\java\\debt-settlement\\App-frontend\\src\\screens\\LandingScreen.js", "source_location": "L5", "weight": 1.0}, {"source": "d_java_debt_settlement_app_frontend_src_screens_landingscreen_js", "target": "lucide_react_native", "relation": "imports_from", "confidence": "EXTRACTED", "source_file": "D:\\java\\debt-settlement\\App-frontend\\src\\screens\\LandingScreen.js", "source_location": "L6", "weight": 1.0}, {"source": "d_java_debt_settlement_app_frontend_src_screens_landingscreen_js", "target": "expo_web_browser", "relation": "imports_from", "confidence": "EXTRACTED", "source_file": "D:\\java\\debt-settlement\\App-frontend\\src\\screens\\LandingScreen.js", "source_location": "L7", "weight": 1.0}, {"source": "d_java_debt_settlement_app_frontend_src_screens_landingscreen_js", "target": "expo_linking", "relation": "imports_from", "confidence": "EXTRACTED", "source_file": "D:\\java\\debt-settlement\\App-frontend\\src\\screens\\LandingScreen.js", "source_location": "L8", "weight": 1.0}, {"source": "d_java_debt_settlement_app_frontend_src_screens_landingscreen_js", "target": "d_java_debt_settlement_app_frontend_src_services_apiservice", "relation": "imports_from", "confidence": "EXTRACTED", "source_file": "D:\\java\\debt-settlement\\App-frontend\\src\\screens\\LandingScreen.js", "source_location": "L9", "weight": 1.0}, {"source": "d_java_debt_settlement_app_frontend_src_screens_landingscreen_js", "target": "d_java_debt_settlement_app_frontend_src_store_usestore", "relation": "imports_from", "confidence": "EXTRACTED", "source_file": "D:\\java\\debt-settlement\\App-frontend\\src\\screens\\LandingScreen.js", "source_location": "L10", "weight": 1.0}, {"source": "d_java_debt_settlement_app_frontend_src_screens_landingscreen_js", "target": "screens_landingscreen_landingscreen", "relation": "contains", "confidence": "EXTRACTED", "source_file": "D:\\java\\debt-settlement\\App-frontend\\src\\screens\\LandingScreen.js", "source_location": "L17", "weight": 1.0}], "raw_calls": [{"caller_nid": "screens_landingscreen_landingscreen", "callee": "useNavigation", "is_member_call": false, "source_file": "D:\\java\\debt-settlement\\App-frontend\\src\\screens\\LandingScreen.js", "source_location": "L18"}, {"caller_nid": "screens_landingscreen_landingscreen", "callee": "useStore", "is_member_call": false, "source_file": "D:\\java\\debt-settlement\\App-frontend\\src\\screens\\LandingScreen.js", "source_location": "L19"}, {"caller_nid": "screens_landingscreen_landingscreen", "callee": "useState", "is_member_call": false, "source_file": "D:\\java\\debt-settlement\\App-frontend\\src\\screens\\LandingScreen.js", "source_location": "L20"}, {"caller_nid": "screens_landingscreen_landingscreen", "callee": "useRef", "is_member_call": false, "source_file": "D:\\java\\debt-settlement\\App-frontend\\src\\screens\\LandingScreen.js", "source_location": "L23"}, {"caller_nid": "screens_landingscreen_landingscreen", "callee": "useRef", "is_member_call": false, "source_file": "D:\\java\\debt-settlement\\App-frontend\\src\\screens\\LandingScreen.js", "source_location": "L24"}, {"caller_nid": "screens_landingscreen_landingscreen", "callee": "useRef", "is_member_call": false, "source_file": "D:\\java\\debt-settlement\\App-frontend\\src\\screens\\LandingScreen.js", "source_location": "L25"}, {"caller_nid": "screens_landingscreen_landingscreen", "callee": "useRef", "is_member_call": false, "source_file": "D:\\java\\debt-settlement\\App-frontend\\src\\screens\\LandingScreen.js", "source_location": "L26"}, {"caller_nid": "screens_landingscreen_landingscreen", "callee": "useEffect", "is_member_call": false, "source_file": "D:\\java\\debt-settlement\\App-frontend\\src\\screens\\LandingScreen.js", "source_location": "L28"}, {"caller_nid": "screens_landingscreen_landingscreen", "callee": "useEffect", "is_member_call": false, "source_file": "D:\\java\\debt-settlement\\App-frontend\\src\\screens\\LandingScreen.js", "source_location": "L69"}, {"caller_nid": "screens_landingscreen_landingscreen", "callee": "require", "is_member_call": false, "source_file": "D:\\java\\debt-settlement\\App-frontend\\src\\screens\\LandingScreen.js", "source_location": "L128"}]}